README.md
setup.cfg
setup.py
bin/littlepy
littlepython/__init__.py
littlepython/ast.py
littlepython/error.py
littlepython/feature.py
littlepython/interpreter.py
littlepython/lp.py
littlepython/parser.py
littlepython/tokenizer.py
littlepython/version.py
littlepython.egg-info/PKG-INFO
littlepython.egg-info/SOURCES.txt
littlepython.egg-info/dependency_links.txt
littlepython.egg-info/not-zip-safe
littlepython.egg-info/requires.txt
littlepython.egg-info/top_level.txt