Metadata-Version: 1.1
Name: littlepython
Version: 0.4.10
Summary: A Super Simplified Python with a Little Syntactic Sugar
Home-page: https://github.com/DerPferd/little-python
Author: Jonathan Beaulieu
Author-email: 123.jonathan@gmail.com
License: MIT
Platform: UNKNOWN
Classifier: Development Status :: 3 - Alpha
Classifier: License :: OSI Approved :: MIT License
Classifier: Intended Audience :: Developers
Classifier: Programming Language :: Python :: 2.7
Classifier: Programming Language :: Python :: 3
Classifier: Programming Language :: Python :: 3.5
Classifier: Programming Language :: Python :: 3.6
